realtime_subtitle/__init__.py
realtime_subtitle/app_config.py
realtime_subtitle/cli.py
realtime_subtitle/common.py
realtime_subtitle/glimmer_speech_recognition.py
realtime_subtitle/parse_audio.py
realtime_subtitle/subtitle.py
realtime_subtitle/template.html
realtime_subtitle/ui.py
realtime_subtitle-0.0.9.dist-info/METADATA
realtime_subtitle-0.0.9.dist-info/WHEEL
realtime_subtitle-0.0.9.dist-info/entry_points.txt
realtime_subtitle-0.0.9.dist-info/licenses/LICENSE
realtime_subtitle-0.0.9.dist-info/RECORD
