Metadata-Version: 2.4
Name: realtime_subtitle
Version: 0.0.9
Summary: realtime subtitle
Project-URL: Homepage, https://github.com/caoqiming/realtime-subtitle
Project-URL: Issues, https://github.com/caoqiming/realtime-subtitle/issues
Author-email: qiming <glimmerddl@gmail.com>
License-Expression: MIT
License-File: LICENSE
Classifier: Operating System :: MacOS
Classifier: Programming Language :: Python :: 3
Requires-Python: >=3.9
Requires-Dist: argostranslate>=1.9.6
Requires-Dist: mlx-whisper==0.4.2
Requires-Dist: numpy>=2.0.2
Requires-Dist: pyaudio>=0.2.14
Requires-Dist: pyqt6==6.9.0
Requires-Dist: scikit-learn>=1.6.1
Requires-Dist: speechbrain==1.0.3
Requires-Dist: torch>=2.7.0
Requires-Dist: translate>=3.6.1
